nonebot_plugin_huaer_bot/__init__.py
nonebot_plugin_huaer_bot/chat.py
nonebot_plugin_huaer_bot/config.py
nonebot_plugin_huaer_bot/config.toml
nonebot_plugin_huaer_bot/doc.py
nonebot_plugin_huaer_bot/group.py
nonebot_plugin_huaer_bot-2.2.3.dist-info/LICENSE
nonebot_plugin_huaer_bot-2.2.3.dist-info/METADATA
nonebot_plugin_huaer_bot-2.2.3.dist-info/WHEEL
nonebot_plugin_huaer_bot-2.2.3.dist-info/RECORD
