Metadata-Version: 2.3
Name: nonebot-plugin-huaer-bot
Version: 2.2.3
Summary: (v2.2.0,新增联网搜索,RAG功能)基于NoneBot的智能对话插件，支持多群组管理和人格定制
License: MIT
Author: HuaEr DevGroup
Author-email: HuaEr_DevGroup@outlook.com
Requires-Python: >=3.10,<4.0
Classifier: License :: OSI Approved :: MIT License
Classifier: Programming Language :: Python :: 3
Classifier: Programming Language :: Python :: 3.10
Classifier: Programming Language :: Python :: 3.11
Classifier: Programming Language :: Python :: 3.12
Classifier: Programming Language :: Python :: 3.13
Requires-Dist: hipporag-lite (>=0.1.1,<0.2.0)
Requires-Dist: httpx (<=1.0.0)
Requires-Dist: nonebot-adapter-onebot (>=2.2.0)
Requires-Dist: nonebot-plugin-htmlrender (>=0.6.6,<0.7.0)
Requires-Dist: nonebot-plugin-localstore (>=0.7.4,<0.8.0)
Requires-Dist: nonebot2 (>=2.3.0)
Requires-Dist: tavily-python (>=0.7.10,<0.8.0)
Requires-Dist: toml (>=0.10.2,<0.11.0)
Project-URL: Repository, https://github.com/inkink365/nonebot-plugin-huaer-bot
